Metadata-Version: 1.2
Name: lazo-index
Version: 0.1
Summary: API for accessing the Lazo index.
Home-page: https://gitlab.com/ViDA-NYU/datamart/lazo-index-service
Author: Fernando Chirigati
Author-email: fchirigati@nyu.edu
Maintainer: Fernando Chirigati
Maintainer-email: fchirigati@nyu.edu
License: BSD-3-Clause
Project-URL: Homepage, https://gitlab.com/ViDA-NYU/datamart/lazo-index-service
Project-URL: Source, https://gitlab.com/ViDA-NYU/datamart/lazo-index-service
Project-URL: Tracker, https://gitlab.com/ViDA-NYU/datamart/lazo-index-service/issues
Keywords: lazo
Platform: UNKNOWN
Classifier: Development Status :: 2 - Pre-Alpha
Classifier: Intended Audience :: Science/Research
Classifier: Natural Language :: English
Classifier: Operating System :: OS Independent
Classifier: Programming Language :: Python :: 3 :: Only
Classifier: Topic :: Scientific/Engineering :: Information Analysis
